{
  "accession_number": "0001562230-26-000005",
  "cik": "0001562230",
  "filing_date": "2026-02-11",
  "firm": "Capital International Investors",
  "holdings": [
    {
      "cusip": "11135F101",
      "name": "BROADCOM INC",
      "share_type": "SH",
      "shares": 141864077,
      "value_usd": 49104488494,
      "weight_pct": "7.70",
      "ticker": "AVGO"
    },
    {
      "cusip": "594918104",
      "name": "MICROSOFT CORP",
      "share_type": "SH",
      "shares": 81585381,
      "value_usd": 39459325693,
      "weight_pct": "6.19",
      "ticker": "MSFT"
    },
    {
      "cusip": "02079K107",
      "name": "ALPHABET INC",
      "share_type": "SH",
      "shares": 84244686,
      "value_usd": 26436598713,
      "weight_pct": "4.14",
      "ticker": "GOOGL"
    },
    {
      "cusip": "037833100",
      "name": "APPLE INC",
      "share_type": "SH",
      "shares": 71822415,
      "value_usd": 19526519857,
      "weight_pct": "3.06",
      "ticker": "AAPL"
    },
    {
      "cusip": "67066G104",
      "name": "NVIDIA CORPORATION",
      "share_type": "SH",
      "shares": 103774772,
      "value_usd": 19354461080,
      "weight_pct": "3.03",
      "ticker": "NVDA"
    },
    {
      "cusip": "30303M102",
      "name": "META PLATFORMS INC",
      "share_type": "SH",
      "shares": 25713823,
      "value_usd": 16974515078,
      "weight_pct": "2.66",
      "ticker": "META"
    },
    {
      "cusip": "718172109",
      "name": "PHILIP MORRIS INTL INC",
      "share_type": "SH",
      "shares": 101377875,
      "value_usd": 16262966904,
      "weight_pct": "2.55",
      "ticker": "PM"
    },
    {
      "cusip": "023135106",
      "name": "AMAZON COM INC",
      "share_type": "SH",
      "shares": 69579830,
      "value_usd": 16061318297,
      "weight_pct": "2.52",
      "ticker": "AMZN"
    },
    {
      "cusip": "369604301",
      "name": "GE AEROSPACE",
      "share_type": "SH",
      "shares": 41885324,
      "value_usd": 12904150144,
      "weight_pct": "2.02",
      "ticker": null
    },
    {
      "cusip": "02079K305",
      "name": "ALPHABET INC",
      "share_type": "SH",
      "shares": 35174241,
      "value_usd": 11009710881,
      "weight_pct": "1.73",
      "ticker": "GOOGL"
    },
    {
      "cusip": "532457108",
      "name": "ELI LILLY & CO",
      "share_type": "SH",
      "shares": 9869380,
      "value_usd": 10606907625,
      "weight_pct": "1.66",
      "ticker": "LLY"
    },
    {
      "cusip": "57636Q104",
      "name": "MASTERCARD INCORPORATED",
      "share_type": "SH",
      "shares": 17964658,
      "value_usd": 10256367968,
      "weight_pct": "1.61",
      "ticker": "MA"
    },
    {
      "cusip": "V7780T103",
      "name": "ROYAL CARIBBEAN GROUP",
      "share_type": "SH",
      "shares": 36165358,
      "value_usd": 10088155677,
      "weight_pct": "1.58",
      "ticker": null
    },
    {
      "cusip": "95040Q104",
      "name": "WELLTOWER INC",
      "share_type": "SH",
      "shares": 47431769,
      "value_usd": 8805411427,
      "weight_pct": "1.38",
      "ticker": "WELL"
    },
    {
      "cusip": "893641100",
      "name": "TRANSDIGM GROUP INC",
      "share_type": "SH",
      "shares": 6544423,
      "value_usd": 8702655463,
      "weight_pct": "1.36",
      "ticker": "TDG"
    },
    {
      "cusip": "46625H100",
      "name": "JPMORGAN CHASE & CO.",
      "share_type": "SH",
      "shares": 26626025,
      "value_usd": 8580167485,
      "weight_pct": "1.34",
      "ticker": "JPM"
    },
    {
      "cusip": "75513E101",
      "name": "RTX CORPORATION",
      "share_type": "SH",
      "shares": 44512309,
      "value_usd": 8164004721,
      "weight_pct": "1.28",
      "ticker": "RTX"
    },
    {
      "cusip": "002824100",
      "name": "ABBOTT LABS",
      "share_type": "SH",
      "shares": 63229445,
      "value_usd": 7922519283,
      "weight_pct": "1.24",
      "ticker": null
    },
    {
      "cusip": "874039100",
      "name": "TAIWAN SEMICONDUCTOR MFG LTD",
      "share_type": "SH",
      "shares": 25658661,
      "value_usd": 7790435276,
      "weight_pct": "1.22",
      "ticker": null
    },
    {
      "cusip": "92826C839",
      "name": "VISA INC",
      "share_type": "SH",
      "shares": 21516371,
      "value_usd": 7547168872,
      "weight_pct": "1.18",
      "ticker": "V"
    },
    {
      "cusip": "482480100",
      "name": "KLA CORP",
      "share_type": "SH",
      "shares": 5450833,
      "value_usd": 6626466959,
      "weight_pct": "1.04",
      "ticker": "KLAC"
    },
    {
      "cusip": "666807102",
      "name": "NORTHROP GRUMMAN CORP",
      "share_type": "SH",
      "shares": 11477634,
      "value_usd": 6545463067,
      "weight_pct": "1.03",
      "ticker": "NOC"
    },
    {
      "cusip": "595112103",
      "name": "MICRON TECHNOLOGY INC",
      "share_type": "SH",
      "shares": 22056387,
      "value_usd": 6296364584,
      "weight_pct": "0.99",
      "ticker": "MU"
    },
    {
      "cusip": "82509L107",
      "name": "SHOPIFY INC",
      "share_type": "SH",
      "shares": 38343155,
      "value_usd": 6174037839,
      "weight_pct": "0.97",
      "ticker": "SHOP"
    },
    {
      "cusip": "91324P102",
      "name": "UNITEDHEALTH GROUP INC",
      "share_type": "SH",
      "shares": 18655111,
      "value_usd": 6158733817,
      "weight_pct": "0.97",
      "ticker": "UNH"
    },
    {
      "cusip": "79466L302",
      "name": "SALESFORCE INC",
      "share_type": "SH",
      "shares": 22721010,
      "value_usd": 6019198862,
      "weight_pct": "0.94",
      "ticker": "CRM"
    },
    {
      "cusip": "031162100",
      "name": "AMGEN INC",
      "share_type": "SH",
      "shares": 18186270,
      "value_usd": 5952964722,
      "weight_pct": "0.93",
      "ticker": "AMGN"
    },
    {
      "cusip": "21037T109",
      "name": "CONSTELLATION ENERGY CORP",
      "share_type": "SH",
      "shares": 16813303,
      "value_usd": 5940971937,
      "weight_pct": "0.93",
      "ticker": "CEG"
    },
    {
      "cusip": "89832Q109",
      "name": "TRUIST FINL CORP",
      "share_type": "SH",
      "shares": 108358164,
      "value_usd": 5332834632,
      "weight_pct": "0.84",
      "ticker": "TFC"
    },
    {
      "cusip": "48251W104",
      "name": "KKR & CO INC",
      "share_type": "SH",
      "shares": 37169932,
      "value_usd": 4738787687,
      "weight_pct": "0.74",
      "ticker": "KKR"
    },
    {
      "cusip": "G1151C101",
      "name": "ACCENTURE PLC IRELAND",
      "share_type": "SH",
      "shares": 17471554,
      "value_usd": 4687867251,
      "weight_pct": "0.73",
      "ticker": null
    },
    {
      "cusip": "609207105",
      "name": "MONDELEZ INTL INC",
      "share_type": "SH",
      "shares": 86943586,
      "value_usd": 4681023814,
      "weight_pct": "0.73",
      "ticker": "MDLZ"
    },
    {
      "cusip": "816851109",
      "name": "SEMPRA",
      "share_type": "SH",
      "shares": 51777703,
      "value_usd": 4572074375,
      "weight_pct": "0.72",
      "ticker": "SRE"
    },
    {
      "cusip": "20825C104",
      "name": "CONOCOPHILLIPS",
      "share_type": "SH",
      "shares": 48360060,
      "value_usd": 4527229824,
      "weight_pct": "0.71",
      "ticker": "COP"
    },
    {
      "cusip": "235851102",
      "name": "DANAHER CORPORATION",
      "share_type": "SH",
      "shares": 18246008,
      "value_usd": 4177385702,
      "weight_pct": "0.65",
      "ticker": "DHR"
    },
    {
      "cusip": "45687V106",
      "name": "INGERSOLL RAND INC",
      "share_type": "SH",
      "shares": 52353914,
      "value_usd": 4147877550,
      "weight_pct": "0.65",
      "ticker": "IR"
    },
    {
      "cusip": "N07059210",
      "name": "ASML HOLDING N V",
      "share_type": "SH",
      "shares": 3409421,
      "value_usd": 3648620242,
      "weight_pct": "0.57",
      "ticker": null
    },
    {
      "cusip": "617446448",
      "name": "MORGAN STANLEY",
      "share_type": "SH",
      "shares": 20544097,
      "value_usd": 3647545244,
      "weight_pct": "0.57",
      "ticker": "MS"
    },
    {
      "cusip": "06849F108",
      "name": "BARRICK MNG CORP",
      "share_type": "SH",
      "shares": 83673678,
      "value_usd": 3646361055,
      "weight_pct": "0.57",
      "ticker": null
    },
    {
      "cusip": "110448107",
      "name": "BRITISH AMERN TOB PLC",
      "share_type": "SH",
      "shares": 64389481,
      "value_usd": 3645500416,
      "weight_pct": "0.57",
      "ticker": null
    },
    {
      "cusip": "571748102",
      "name": "MARSH & MCLENNAN COS INC",
      "share_type": "SH",
      "shares": 18766815,
      "value_usd": 3482556927,
      "weight_pct": "0.55",
      "ticker": null
    },
    {
      "cusip": "58733R102",
      "name": "MERCADOLIBRE INC",
      "share_type": "SH",
      "shares": 1725125,
      "value_usd": 3474880152,
      "weight_pct": "0.54",
      "ticker": "MELI"
    },
    {
      "cusip": "F92124100",
      "name": "TOTALENERGIES SE",
      "share_type": "SH",
      "shares": 52668676,
      "value_usd": 3435988140,
      "weight_pct": "0.54",
      "ticker": "TTE"
    },
    {
      "cusip": "743315103",
      "name": "PROGRESSIVE CORP",
      "share_type": "SH",
      "shares": 14921724,
      "value_usd": 3398123364,
      "weight_pct": "0.53",
      "ticker": "PGR"
    },
    {
      "cusip": "704326107",
      "name": "PAYCHEX INC",
      "share_type": "SH",
      "shares": 30265174,
      "value_usd": 3395583196,
      "weight_pct": "0.53",
      "ticker": "PAYX"
    },
    {
      "cusip": "15189T107",
      "name": "CENTERPOINT ENERGY INC",
      "share_type": "SH",
      "shares": 86030252,
      "value_usd": 3298763050,
      "weight_pct": "0.52",
      "ticker": "CNP"
    },
    {
      "cusip": "G54950103",
      "name": "LINDE PLC",
      "share_type": "SH",
      "shares": 7610387,
      "value_usd": 3245254754,
      "weight_pct": "0.51",
      "ticker": "LIN"
    },
    {
      "cusip": "032095101",
      "name": "AMPHENOL CORP NEW",
      "share_type": "SH",
      "shares": 23680749,
      "value_usd": 3200275744,
      "weight_pct": "0.50",
      "ticker": "APH"
    },
    {
      "cusip": "009158106",
      "name": "AIR PRODS & CHEMS INC",
      "share_type": "SH",
      "shares": 12792580,
      "value_usd": 3160023492,
      "weight_pct": "0.50",
      "ticker": null
    },
    {
      "cusip": "594972408",
      "name": "STRATEGY INC",
      "share_type": "SH",
      "shares": 20614868,
      "value_usd": 3132459695,
      "weight_pct": "0.49",
      "ticker": "MSTR"
    }
  ],
  "investor": "Capital International Investors",
  "period": "2025-12-31",
  "total_holdings": 454,
  "total_value_usd": 637974701306
}